aakit/__init__.py
aakit/cli.py
aakit/config.py
aakit/core/__init__.py
aakit/core/agent.py
aakit/core/cache_manager.py
aakit/core/circuit_breaker.py
aakit/core/config.py
aakit/core/connection_manager.py
aakit/core/conversation.py
aakit/core/exceptions.py
aakit/core/lifecycle_manager.py
aakit/core/observability.py
aakit/core/parallel_executor.py
aakit/core/rate_limiter.py
aakit/core/retry_manager.py
aakit/core/streaming_manager.py
aakit/core/timeout_manager.py
aakit/llm/__init__.py
aakit/llm/manager.py
aakit/llm/manager_backup.py
aakit/llm/production_features.py
aakit/llm/providers.py
aakit/mcp/__init__.py
aakit/mcp/client.py
aakit/mcp/server.py
aakit/memory/__init__.py
aakit/memory/backends.py
aakit/memory/factory.py
aakit/reasoning/__init__.py
aakit/reasoning/factory.py
aakit/reasoning/patterns.py
aakit/server/__init__.py
aakit/tests/test_agent.py
aakit/tests/test_features.py
aakit/tools/__init__.py
aakit/tools/decorators.py
aakit/tools/registry.py
aakit/tools/schema.py
aakit/utils/__init__.py
aa_kit-0.3.0.dist-info/METADATA
aa_kit-0.3.0.dist-info/WHEEL
aa_kit-0.3.0.dist-info/entry_points.txt
aa_kit-0.3.0.dist-info/top_level.txt
aa_kit-0.3.0.dist-info/RECORD
