Metadata-Version: 2.4
Name: aa-kit
Version: 0.3.0
Summary: The Universal AI Agent Framework for the MCP Era
Home-page: https://github.com/josharsh/aa-kit
Author: Harsh Joshi
Author-email: Harsh Joshi <harsh.joshi.pth@gmail.com>
Maintainer-email: Harsh Joshi <harsh.joshi.pth@gmail.com>
License: MIT
Project-URL: Homepage, https://aa-kit.dev
Project-URL: Documentation, https://docs.aa-kit.dev
Project-URL: Repository, https://github.com/josharsh/aa-kit
Project-URL: Bug Reports, https://github.com/josharsh/aa-kit/issues
Project-URL: Funding, https://github.com/sponsors/josharsh
Keywords: ai,agents,mcp,llm,openai,anthropic,framework
Classifier: Development Status :: 4 - Beta
Classifier: Intended Audience :: Developers
Classifier: License :: OSI Approved :: MIT License
Classifier: Programming Language :: Python :: 3
Classifier: Programming Language :: Python :: 3.9
Classifier: Programming Language :: Python :: 3.10
Classifier: Programming Language :: Python :: 3.11
Classifier: Programming Language :: Python :: 3.12
Classifier: Topic :: Software Development :: Libraries :: Python Modules
Classifier: Topic :: Scientific/Engineering :: Artificial Intelligence
Requires-Python: >=3.8
Requires-Dist: openai>=1.0.0
Requires-Dist: anthropic>=0.8.0
Requires-Dist: pydantic>=2.0.0
Requires-Dist: aiohttp>=3.8.0
Requires-Dist: uvicorn>=0.20.0
Requires-Dist: fastapi>=0.95.0
Requires-Dist: websockets>=11.0.0
Requires-Dist: redis>=4.5.0
Requires-Dist: aiosqlite>=0.19.0
Requires-Dist: asyncpg>=0.28.0
Requires-Dist: rich>=13.0.0
Requires-Dist: typer>=0.9.0
Requires-Dist: python-dotenv>=1.0.0
Requires-Dist: httpx>=0.24.0
Provides-Extra: dev
Requires-Dist: pytest>=7.0.0; extra == "dev"
Requires-Dist: pytest-asyncio>=0.21.0; extra == "dev"
Requires-Dist: pytest-mock>=3.10.0; extra == "dev"
Requires-Dist: black>=23.0.0; extra == "dev"
Requires-Dist: isort>=5.12.0; extra == "dev"
Requires-Dist: mypy>=1.0.0; extra == "dev"
Requires-Dist: ruff>=0.0.260; extra == "dev"
Requires-Dist: pre-commit>=3.0.0; extra == "dev"
Provides-Extra: docs
Requires-Dist: mkdocs>=1.4.0; extra == "docs"
Requires-Dist: mkdocs-material>=9.0.0; extra == "docs"
Requires-Dist: mkdocs-mermaid2-plugin>=0.6.0; extra == "docs"
Provides-Extra: all
Requires-Dist: aa-kit[dev,docs]; extra == "all"
Dynamic: author
Dynamic: home-page
Dynamic: requires-python
